variant_tools/__init__.py
variant_tools/alignment.py
variant_tools/cli.py
variant_tools/mutalyzer.py
variant_tools/str_search.py
variant_tools/utils.py
variant_tools/variant_calling.py
variant_tools/vcf_tools.py
pgx_variant_tools-0.0.3.dist-info/LICENSE
pgx_variant_tools-0.0.3.dist-info/METADATA
pgx_variant_tools-0.0.3.dist-info/WHEEL
pgx_variant_tools-0.0.3.dist-info/entry_points.txt
pgx_variant_tools-0.0.3.dist-info/top_level.txt
pgx_variant_tools-0.0.3.dist-info/RECORD
